hi/__init__.py
hi/cli.py
hi/data/pwned.txt
hi/data/secrets.zip
hi_fish-0.0.2.dist-info/METADATA
hi_fish-0.0.2.dist-info/WHEEL
hi_fish-0.0.2.dist-info/entry_points.txt
hi_fish-0.0.2.dist-info/top_level.txt
hi_fish-0.0.2.dist-info/RECORD
